{
  "things-style@@h5-color": "#6D1818",
  "things-style@@strong-color": "#680E31",
  "things-style@@em-color": "#6D062E",
  "things-style@@h4-color": "#0D4452",
  "things-style@@h3-color": "#104B9D",
  "things-style@@h2-color": "#123F7F",
  "things-style@@h2-underline": true,
  "Components@@CTA-BTN-enable": false,
  "Components@@file-names-untrim": false,
  "Components@@folder-font-bold": true,
  "Components@@file-icon-remove": false,
  "Components@@colorful-folder": true,
  "Components@@outline-enhanced": false,
  "Components@@new-tab-btn-select": "new-tab-btn-default",
  "Components@@immersive-canvas": false,
  "Components@@media-embed-card-border-off": false,
  "Components@@scrollbar-hide": false,
  "Components@@restored-scrollbars": false,
  "Components@@setting-item-title-icon-remove": false,
  "Appearance-light@@card-layout-open-light": true
}
